README.rst
setup.cfg
setup.py
phishnetpy/__init__.py
phishnetpy/decorators.py
phishnetpy/exceptions.py
phishnetpy/phishnet_api.py
phishnetpy.egg-info/PKG-INFO
phishnetpy.egg-info/SOURCES.txt
phishnetpy.egg-info/dependency_links.txt
phishnetpy.egg-info/requires.txt
phishnetpy.egg-info/top_level.txt