Metadata-Version: 1.1
Name: phishnetpy
Version: 0.2.4
Summary: Python client for the Phish.net API
Home-page: https://github.com/jameserrico/phishnetpy
Author: James Errico
Author-email: james.errico@gmail.com
License: MIT
Keywords: phish phish.net client
Platform: UNKNOWN
Classifier: Development Status :: 4 - Beta
Classifier: Intended Audience :: Developers
Classifier: License :: OSI Approved :: MIT License
Classifier: Programming Language :: Python
Classifier: Programming Language :: Python :: 3
Classifier: Programming Language :: Python :: 2.7
Classifier: Programming Language :: Python :: 3.4
